daft/__init__.py
daft/_core.py
daft/_exceptions.py
daft/_utils.py
daft_pgm-0.1.4.dist-info/LICENSE.rst
daft_pgm-0.1.4.dist-info/METADATA
daft_pgm-0.1.4.dist-info/WHEEL
daft_pgm-0.1.4.dist-info/top_level.txt
daft_pgm-0.1.4.dist-info/RECORD
